modelvis.py
modelvis-0.1.7.dist-info/METADATA
modelvis-0.1.7.dist-info/RECORD
modelvis-0.1.7.dist-info/WHEEL
modelvis-0.1.7.dist-info/top_level.txt
